{"Status":3,"TimeLimitReached":true,"RunningTime":"00:10:00.9340000","StartTimes":[{"JobIndex":0,"StartTime":46},{"JobIndex":1,"StartTime":49},{"JobIndex":2,"StartTime":9},{"JobIndex":3,"StartTime":87},{"JobIndex":4,"StartTime":10},{"JobIndex":5,"StartTime":11},{"JobIndex":6,"StartTime":32},{"JobIndex":7,"StartTime":34},{"JobIndex":8,"StartTime":79},{"JobIndex":9,"StartTime":92},{"JobIndex":10,"StartTime":12},{"JobIndex":11,"StartTime":13},{"JobIndex":12,"StartTime":97},{"JobIndex":13,"StartTime":102},{"JobIndex":14,"StartTime":36},{"JobIndex":15,"StartTime":107},{"JobIndex":16,"StartTime":112},{"JobIndex":17,"StartTime":38},{"JobIndex":18,"StartTime":52},{"JobIndex":19,"StartTime":83},{"JobIndex":20,"StartTime":127},{"JobIndex":21,"StartTime":14},{"JobIndex":22,"StartTime":40},{"JobIndex":23,"StartTime":15},{"JobIndex":24,"StartTime":31},{"JobIndex":25,"StartTime":42},{"JobIndex":26,"StartTime":117},{"JobIndex":27,"StartTime":122},{"JobIndex":28,"StartTime":131},{"JobIndex":29,"StartTime":158},{"JobIndex":30,"StartTime":139},{"JobIndex":31,"StartTime":159},{"JobIndex":32,"StartTime":44},{"JobIndex":33,"StartTime":55},{"JobIndex":34,"StartTime":58},{"JobIndex":35,"StartTime":135},{"JobIndex":36,"StartTime":160},{"JobIndex":37,"StartTime":61},{"JobIndex":38,"StartTime":161},{"JobIndex":39,"StartTime":144},{"JobIndex":40,"StartTime":64},{"JobIndex":41,"StartTime":165},{"JobIndex":42,"StartTime":149},{"JobIndex":43,"StartTime":67},{"JobIndex":44,"StartTime":70},{"JobIndex":45,"StartTime":167},{"JobIndex":46,"StartTime":172},{"JobIndex":47,"StartTime":163},{"JobIndex":48,"StartTime":164},{"JobIndex":49,"StartTime":180},{"JobIndex":50,"StartTime":181},{"JobIndex":51,"StartTime":182},{"JobIndex":52,"StartTime":154},{"JobIndex":53,"StartTime":73},{"JobIndex":54,"StartTime":76},{"JobIndex":55,"StartTime":177},{"JobIndex":56,"StartTime":197},{"JobIndex":57,"StartTime":187},{"JobIndex":58,"StartTime":192},{"JobIndex":59,"StartTime":198}],"LowerBound":1512.0,"Objective":3984,"TimeToBest":null,"Metadata":null,"AdditionalInfo":{"NumNodes":43214934,"NumFails":19599308,"SearchSpeed":72062.1}}