{"Status":3,"TimeLimitReached":true,"RunningTime":"00:10:00.7560000","StartTimes":[{"JobIndex":0,"StartTime":87},{"JobIndex":1,"StartTime":19},{"JobIndex":2,"StartTime":15},{"JobIndex":3,"StartTime":22},{"JobIndex":4,"StartTime":47},{"JobIndex":5,"StartTime":83},{"JobIndex":6,"StartTime":88},{"JobIndex":7,"StartTime":91},{"JobIndex":8,"StartTime":163},{"JobIndex":9,"StartTime":27},{"JobIndex":10,"StartTime":85},{"JobIndex":11,"StartTime":94},{"JobIndex":12,"StartTime":164},{"JobIndex":13,"StartTime":32},{"JobIndex":14,"StartTime":37},{"JobIndex":15,"StartTime":97},{"JobIndex":16,"StartTime":42},{"JobIndex":17,"StartTime":115},{"JobIndex":18,"StartTime":103},{"JobIndex":19,"StartTime":100},{"JobIndex":20,"StartTime":172},{"JobIndex":21,"StartTime":178},{"JobIndex":22,"StartTime":179},{"JobIndex":23,"StartTime":121},{"JobIndex":24,"StartTime":50},{"JobIndex":25,"StartTime":117},{"JobIndex":26,"StartTime":180},{"JobIndex":27,"StartTime":55},{"JobIndex":28,"StartTime":107},{"JobIndex":29,"StartTime":181},{"JobIndex":30,"StartTime":131},{"JobIndex":31,"StartTime":127},{"JobIndex":32,"StartTime":112},{"JobIndex":33,"StartTime":123},{"JobIndex":34,"StartTime":141},{"JobIndex":35,"StartTime":191},{"JobIndex":36,"StartTime":195},{"JobIndex":37,"StartTime":136},{"JobIndex":38,"StartTime":149},{"JobIndex":39,"StartTime":129},{"JobIndex":40,"StartTime":152},{"JobIndex":41,"StartTime":159},{"JobIndex":42,"StartTime":196},{"JobIndex":43,"StartTime":197},{"JobIndex":44,"StartTime":155},{"JobIndex":45,"StartTime":165},{"JobIndex":46,"StartTime":198},{"JobIndex":47,"StartTime":161},{"JobIndex":48,"StartTime":202},{"JobIndex":49,"StartTime":182},{"JobIndex":50,"StartTime":169},{"JobIndex":51,"StartTime":144},{"JobIndex":52,"StartTime":204},{"JobIndex":53,"StartTime":207},{"JobIndex":54,"StartTime":205},{"JobIndex":55,"StartTime":208},{"JobIndex":56,"StartTime":192},{"JobIndex":57,"StartTime":199},{"JobIndex":58,"StartTime":173},{"JobIndex":59,"StartTime":186}],"LowerBound":1448.0,"Objective":3689,"TimeToBest":null,"Metadata":null,"AdditionalInfo":{"NumNodes":50869953,"NumFails":23193837,"SearchSpeed":84839.8}}