{"Status":1,"TimeLimitReached":false,"RunningTime":"00:00:07.3540000","StartTimes":[{"JobIndex":0,"StartTime":4},{"JobIndex":1,"StartTime":12},{"JobIndex":2,"StartTime":34},{"JobIndex":3,"StartTime":187},{"JobIndex":4,"StartTime":82},{"JobIndex":5,"StartTime":21},{"JobIndex":6,"StartTime":17},{"JobIndex":7,"StartTime":51},{"JobIndex":8,"StartTime":7},{"JobIndex":9,"StartTime":96},{"JobIndex":10,"StartTime":191},{"JobIndex":11,"StartTime":29},{"JobIndex":12,"StartTime":9},{"JobIndex":13,"StartTime":18},{"JobIndex":14,"StartTime":54},{"JobIndex":15,"StartTime":87},{"JobIndex":16,"StartTime":99},{"JobIndex":17,"StartTime":102},{"JobIndex":18,"StartTime":16},{"JobIndex":19,"StartTime":166},{"JobIndex":20,"StartTime":48},{"JobIndex":21,"StartTime":104},{"JobIndex":22,"StartTime":107},{"JobIndex":23,"StartTime":37},{"JobIndex":24,"StartTime":88},{"JobIndex":25,"StartTime":65},{"JobIndex":26,"StartTime":110},{"JobIndex":27,"StartTime":192},{"JobIndex":28,"StartTime":112},{"JobIndex":29,"StartTime":58},{"JobIndex":30,"StartTime":40},{"JobIndex":31,"StartTime":115},{"JobIndex":32,"StartTime":45},{"JobIndex":33,"StartTime":138},{"JobIndex":34,"StartTime":120},{"JobIndex":35,"StartTime":11},{"JobIndex":36,"StartTime":125},{"JobIndex":37,"StartTime":24},{"JobIndex":38,"StartTime":189},{"JobIndex":39,"StartTime":135},{"JobIndex":40,"StartTime":155},{"JobIndex":41,"StartTime":39},{"JobIndex":42,"StartTime":128},{"JobIndex":43,"StartTime":163},{"JobIndex":44,"StartTime":180},{"JobIndex":45,"StartTime":131},{"JobIndex":46,"StartTime":172},{"JobIndex":47,"StartTime":62},{"JobIndex":48,"StartTime":69},{"JobIndex":49,"StartTime":182},{"JobIndex":50,"StartTime":159},{"JobIndex":51,"StartTime":169},{"JobIndex":52,"StartTime":194},{"JobIndex":53,"StartTime":176},{"JobIndex":54,"StartTime":72},{"JobIndex":55,"StartTime":91},{"JobIndex":56,"StartTime":28},{"JobIndex":57,"StartTime":33},{"JobIndex":58,"StartTime":77},{"JobIndex":59,"StartTime":164}],"LowerBound":3764.0,"Objective":3764,"TimeToBest":null,"Metadata":null,"AdditionalInfo":null}