{"Status":1,"TimeLimitReached":false,"RunningTime":"00:22:27.9780000","StartTimes":[{"JobIndex":0,"StartTime":368},{"JobIndex":1,"StartTime":82},{"JobIndex":2,"StartTime":678},{"JobIndex":3,"StartTime":298},{"JobIndex":4,"StartTime":783},{"JobIndex":5,"StartTime":864},{"JobIndex":6,"StartTime":408},{"JobIndex":7,"StartTime":818},{"JobIndex":8,"StartTime":688},{"JobIndex":9,"StartTime":1183},{"JobIndex":10,"StartTime":277},{"JobIndex":11,"StartTime":147},{"JobIndex":12,"StartTime":404},{"JobIndex":13,"StartTime":321},{"JobIndex":14,"StartTime":858},{"JobIndex":15,"StartTime":759},{"JobIndex":16,"StartTime":816},{"JobIndex":17,"StartTime":213},{"JobIndex":18,"StartTime":917},{"JobIndex":19,"StartTime":1158},{"JobIndex":20,"StartTime":331},{"JobIndex":21,"StartTime":923},{"JobIndex":22,"StartTime":564},{"JobIndex":23,"StartTime":61},{"JobIndex":24,"StartTime":125},{"JobIndex":25,"StartTime":918},{"JobIndex":26,"StartTime":374},{"JobIndex":27,"StartTime":42},{"JobIndex":28,"StartTime":395},{"JobIndex":29,"StartTime":327},{"JobIndex":30,"StartTime":201},{"JobIndex":31,"StartTime":10},{"JobIndex":32,"StartTime":851},{"JobIndex":33,"StartTime":345},{"JobIndex":34,"StartTime":117},{"JobIndex":35,"StartTime":704},{"JobIndex":36,"StartTime":951},{"JobIndex":37,"StartTime":206},{"JobIndex":38,"StartTime":748},{"JobIndex":39,"StartTime":874},{"JobIndex":40,"StartTime":945},{"JobIndex":41,"StartTime":731},{"JobIndex":42,"StartTime":562},{"JobIndex":43,"StartTime":1182},{"JobIndex":44,"StartTime":86},{"JobIndex":45,"StartTime":56},{"JobIndex":46,"StartTime":356},{"JobIndex":47,"StartTime":471},{"JobIndex":48,"StartTime":27},{"JobIndex":49,"StartTime":152},{"JobIndex":50,"StartTime":742},{"JobIndex":51,"StartTime":306},{"JobIndex":52,"StartTime":109},{"JobIndex":53,"StartTime":70},{"JobIndex":54,"StartTime":754},{"JobIndex":55,"StartTime":290},{"JobIndex":56,"StartTime":677},{"JobIndex":57,"StartTime":316},{"JobIndex":58,"StartTime":1093},{"JobIndex":59,"StartTime":101},{"JobIndex":60,"StartTime":785},{"JobIndex":61,"StartTime":763},{"JobIndex":62,"StartTime":310},{"JobIndex":63,"StartTime":97},{"JobIndex":64,"StartTime":501},{"JobIndex":65,"StartTime":293},{"JobIndex":66,"StartTime":391},{"JobIndex":67,"StartTime":939},{"JobIndex":68,"StartTime":4},{"JobIndex":69,"StartTime":929},{"JobIndex":70,"StartTime":1178},{"JobIndex":71,"StartTime":128},{"JobIndex":72,"StartTime":41},{"JobIndex":73,"StartTime":295},{"JobIndex":74,"StartTime":98},{"JobIndex":75,"StartTime":1170},{"JobIndex":76,"StartTime":693},{"JobIndex":77,"StartTime":1163},{"JobIndex":78,"StartTime":76},{"JobIndex":79,"StartTime":157},{"JobIndex":80,"StartTime":698},{"JobIndex":81,"StartTime":852},{"JobIndex":82,"StartTime":948},{"JobIndex":83,"StartTime":31},{"JobIndex":84,"StartTime":508},{"JobIndex":85,"StartTime":1000},{"JobIndex":86,"StartTime":349},{"JobIndex":87,"StartTime":561},{"JobIndex":88,"StartTime":340},{"JobIndex":89,"StartTime":36},{"JobIndex":90,"StartTime":354},{"JobIndex":91,"StartTime":73},{"JobIndex":92,"StartTime":359},{"JobIndex":93,"StartTime":382},{"JobIndex":94,"StartTime":133},{"JobIndex":95,"StartTime":17},{"JobIndex":96,"StartTime":853},{"JobIndex":97,"StartTime":143},{"JobIndex":98,"StartTime":104},{"JobIndex":99,"StartTime":1091},{"JobIndex":100,"StartTime":312},{"JobIndex":101,"StartTime":952},{"JobIndex":102,"StartTime":746},{"JobIndex":103,"StartTime":861},{"JobIndex":104,"StartTime":288},{"JobIndex":105,"StartTime":778},{"JobIndex":106,"StartTime":284},{"JobIndex":107,"StartTime":1002},{"JobIndex":108,"StartTime":387},{"JobIndex":109,"StartTime":363},{"JobIndex":110,"StartTime":114},{"JobIndex":111,"StartTime":1101},{"JobIndex":112,"StartTime":103},{"JobIndex":113,"StartTime":400},{"JobIndex":114,"StartTime":1191},{"JobIndex":115,"StartTime":209},{"JobIndex":116,"StartTime":71},{"JobIndex":117,"StartTime":739},{"JobIndex":118,"StartTime":218},{"JobIndex":119,"StartTime":12},{"JobIndex":120,"StartTime":819},{"JobIndex":121,"StartTime":153},{"JobIndex":122,"StartTime":294},{"JobIndex":123,"StartTime":1090},{"JobIndex":124,"StartTime":683},{"JobIndex":125,"StartTime":871},{"JobIndex":126,"StartTime":938},{"JobIndex":127,"StartTime":226},{"JobIndex":128,"StartTime":934},{"JobIndex":129,"StartTime":222},{"JobIndex":130,"StartTime":75},{"JobIndex":131,"StartTime":336},{"JobIndex":132,"StartTime":220},{"JobIndex":133,"StartTime":789},{"JobIndex":134,"StartTime":80},{"JobIndex":135,"StartTime":955},{"JobIndex":136,"StartTime":44},{"JobIndex":137,"StartTime":912},{"JobIndex":138,"StartTime":332},{"JobIndex":139,"StartTime":55},{"JobIndex":140,"StartTime":52},{"JobIndex":141,"StartTime":274},{"JobIndex":142,"StartTime":732},{"JobIndex":143,"StartTime":753},{"JobIndex":144,"StartTime":473},{"JobIndex":145,"StartTime":1175},{"JobIndex":146,"StartTime":944},{"JobIndex":147,"StartTime":372},{"JobIndex":148,"StartTime":350},{"JobIndex":149,"StartTime":1098},{"JobIndex":150,"StartTime":771},{"JobIndex":151,"StartTime":768},{"JobIndex":152,"StartTime":335},{"JobIndex":153,"StartTime":137},{"JobIndex":154,"StartTime":1099},{"JobIndex":155,"StartTime":49},{"JobIndex":156,"StartTime":1185},{"JobIndex":157,"StartTime":386},{"JobIndex":158,"StartTime":774},{"JobIndex":159,"StartTime":120},{"JobIndex":160,"StartTime":1006},{"JobIndex":161,"StartTime":314},{"JobIndex":162,"StartTime":219},{"JobIndex":163,"StartTime":1165},{"JobIndex":164,"StartTime":57},{"JobIndex":165,"StartTime":22},{"JobIndex":166,"StartTime":324},{"JobIndex":167,"StartTime":930},{"JobIndex":168,"StartTime":866},{"JobIndex":169,"StartTime":301},{"JobIndex":170,"StartTime":5},{"JobIndex":171,"StartTime":84},{"JobIndex":172,"StartTime":503},{"JobIndex":173,"StartTime":62},{"JobIndex":174,"StartTime":111},{"JobIndex":175,"StartTime":1196},{"JobIndex":176,"StartTime":476},{"JobIndex":177,"StartTime":960},{"JobIndex":178,"StartTime":925},{"JobIndex":179,"StartTime":145},{"JobIndex":180,"StartTime":402},{"JobIndex":181,"StartTime":377},{"JobIndex":182,"StartTime":280},{"JobIndex":183,"StartTime":409},{"JobIndex":184,"StartTime":142},{"JobIndex":185,"StartTime":701},{"JobIndex":186,"StartTime":67},{"JobIndex":187,"StartTime":1188},{"JobIndex":188,"StartTime":21},{"JobIndex":189,"StartTime":735}],"LowerBound":11465.0,"Objective":11465,"TimeToBest":null,"Metadata":null}