{"Status":1,"TimeLimitReached":false,"RunningTime":"00:00:01.2600000","StartTimes":[{"JobIndex":0,"StartTime":59},{"JobIndex":1,"StartTime":26},{"JobIndex":2,"StartTime":101},{"JobIndex":3,"StartTime":4},{"JobIndex":4,"StartTime":10},{"JobIndex":5,"StartTime":46},{"JobIndex":6,"StartTime":27},{"JobIndex":7,"StartTime":73},{"JobIndex":8,"StartTime":8},{"JobIndex":9,"StartTime":48},{"JobIndex":10,"StartTime":39},{"JobIndex":11,"StartTime":37},{"JobIndex":12,"StartTime":98},{"JobIndex":13,"StartTime":56},{"JobIndex":14,"StartTime":96},{"JobIndex":15,"StartTime":24},{"JobIndex":16,"StartTime":21},{"JobIndex":17,"StartTime":58},{"JobIndex":18,"StartTime":31},{"JobIndex":19,"StartTime":76},{"JobIndex":20,"StartTime":11},{"JobIndex":21,"StartTime":36},{"JobIndex":22,"StartTime":20},{"JobIndex":23,"StartTime":52},{"JobIndex":24,"StartTime":91},{"JobIndex":25,"StartTime":17},{"JobIndex":26,"StartTime":7},{"JobIndex":27,"StartTime":13},{"JobIndex":28,"StartTime":9},{"JobIndex":29,"StartTime":41}],"LowerBound":1426.0,"Objective":1426,"TimeToBest":null,"Metadata":null}